py_simple_messenger_server-0.0.1.data/scripts/server_run
server/__init__.py
server/server_main.py
server/common/__init__.py
server/common/constants.py
server/common/decorators.py
server/common/descriptors.py
server/common/errors.py
server/common/metaclasses.py
server/common/utils.py
server/log/__init__.py
server/log/client_log_config.py
server/log/server_log_config.py
server/server/__init__.py
server/server/add_user.py
server/server/config_window.py
server/server/core.py
server/server/database.py
server/server/main_window.py
server/server/remove_user.py
server/server/stat_window.py
server/unit_tests/__init__.py
server/unit_tests/test_client.py
server/unit_tests/test_server.py
server/unit_tests/test_utils.py
py_simple_messenger_server-0.0.1.dist-info/METADATA
py_simple_messenger_server-0.0.1.dist-info/WHEEL
py_simple_messenger_server-0.0.1.dist-info/top_level.txt
py_simple_messenger_server-0.0.1.dist-info/RECORD
