Metadata-Version: 2.1
Name: py-simple-messenger-server
Version: 0.0.1
Summary: Simple messenger server
Home-page: UNKNOWN
Author: Andrey Yablokov
Author-email: andrewyablokov@yandex.ru
License: UNKNOWN
Platform: UNKNOWN
Requires-Dist: PyQt5
Requires-Dist: sqlalchemy
Requires-Dist: pycryptodome
Requires-Dist: pycryptodomex
